kmqc/__init__.py
kmqc/api.py
kmqc/base.py
kmqc/config.py
kmqc/gates.py
kmqc/program.py
kmqc-1.0.1.1.dist-info/LICENSE
kmqc-1.0.1.1.dist-info/METADATA
kmqc-1.0.1.1.dist-info/WHEEL
kmqc-1.0.1.1.dist-info/top_level.txt
kmqc-1.0.1.1.dist-info/RECORD
