Metadata-Version: 2.1
Name: kmqc
Version: 1.0.1.1
Summary: A package for client
Home-page: https://bitbucket.org/rstm-sf/pykmqc
Author: Rustam Sayfutdinov
Author-email: rstm-sf@gmail.com
License: UNKNOWN
Keywords: sdk quantum programming
Platform: UNKNOWN
Classifier: Programming Language :: Python :: 3
Classifier: License :: OSI Approved :: MIT License
Classifier: Operating System :: OS Independent
Requires-Dist: requests
Requires-Dist: six
